relay/__init__.py
relay/bindings.py
relay/consts.py
relay/event.py
relay/relay.py
relay/utils.py
relaypy_async-0.1.1.dist-info/LICENSE
relaypy_async-0.1.1.dist-info/METADATA
relaypy_async-0.1.1.dist-info/WHEEL
relaypy_async-0.1.1.dist-info/top_level.txt
relaypy_async-0.1.1.dist-info/RECORD
