Metadata-Version: 2.1
Name: relaypy-async
Version: 0.1.1
Summary: Relay is a Python package providing an asynchronous event system in a class, enabling easy inter-method communication. It automatically validates emitted data against provided type hints and facilitates setting up complex event emitting-listening configurations through easy bindings creation.
Home-page: https://github.com/dim-4/relay
Author: Vos
Author-email: your.email@example.com
License: UNKNOWN
Platform: UNKNOWN
Classifier: Development Status :: 3 - Alpha
Classifier: Intended Audience :: Developers
Classifier: License :: OSI Approved :: MIT License
Classifier: Programming Language :: Python :: 3.10
Classifier: Programming Language :: Python :: 3.11
License-File: LICENSE
Requires-Dist: asyncio
Requires-Dist: pydantic
